README.md
setup.py
chunithm_scraper/__init__.py
chunithm_scraper/main.py
chunithm_scraper.egg-info/PKG-INFO
chunithm_scraper.egg-info/SOURCES.txt
chunithm_scraper.egg-info/dependency_links.txt
chunithm_scraper.egg-info/requires.txt
chunithm_scraper.egg-info/top_level.txt