Metadata-Version: 2.1
Name: chunithm_scraper
Version: 1.0.3
Summary: A scraper for chunithm-net.com
Home-page: https://github.com/taka-4602/ONGEKI.Net-CHUNITHM.Net-Scraper
Author: taka4602
Author-email: takaka4602@gmail.com
Keywords: chunithm
Classifier: Programming Language :: Python :: 3
Classifier: License :: OSI Approved :: MIT License
Classifier: Operating System :: OS Independent
Requires-Python: >=3.6
Requires-Dist: requests
Requires-Dist: bs4
